{
  "products": [
    {
      "id": 1,
      "name": "Blue Shirt",
      "type": "shirt",
      "level": 1,
      "price": 10,
      "texture": "wip-product.png",
      "effect": [
        {"method": "click-power", "action": "increment", "amount": 1}
      ]
    },
    {
      "id": 2,
      "name": "Red Shirt",
      "type": "shirt",
      "level": 2,
      "price": 20,
      "texture": "wip-product.png",
      "effect": [
        {"method": "click-power", "action": "increment", "amount": 1}
      ]
    },
    {
      "id": 3,
      "name": "Green Shirt",
      "type": "shirt",
      "level": 3,
      "price": 30,
      "texture": "wip-product.png",
      "effect": [
        {"method": "click-power", "action": "increment", "amount": 1}
      ]
    },
    {
      "id": 3,
      "name": "Green Shirt",
      "type": "shirt",
      "level": 3,
      "price": 30,
      "texture": "wip-product.png",
      "effect": [
        {"method": "click-power", "action": "increment", "amount": 1}
      ]
    },
    {
      "id": 3,
      "name": "Green Shirt",
      "type": "shirt",
      "level": 3,
      "price": 30,
      "texture": "wip-product.png",
      "effect": [
        {"method": "click-power", "action": "increment", "amount": 1}
      ]
    },
    {
      "id": 3,
      "name": "Green Shirt",
      "type": "shirt",
      "level": 3,
      "price": 30,
      "texture": "wip-product.png",
      "effect": [
        {"method": "click-power", "action": "increment", "amount": 1}
      ]
    },
    {
      "id": 3,
      "name": "Green Shirt",
      "type": "shirt",
      "level": 3,
      "price": 30,
      "texture": "wip-product.png",
      "effect": [
        {"method": "click-power", "action": "increment", "amount": 1}
      ]
    },
    {
      "id": 3,
      "name": "Green Shirt",
      "type": "shirt",
      "level": 3,
      "price": 30,
      "texture": "wip-product.png",
      "effect": [
        {"method": "click-power", "action": "increment", "amount": 1}
      ]
    }
  ]
}